cloudsplaining/__init__.py
cloudsplaining/py.typed
cloudsplaining/bin/__init__.py
cloudsplaining/bin/cli.py
cloudsplaining/bin/version.py
cloudsplaining/command/__init__.py
cloudsplaining/command/create_exclusions_file.py
cloudsplaining/command/create_multi_account_config_file.py
cloudsplaining/command/download.py
cloudsplaining/command/expand_policy.py
cloudsplaining/command/scan.py
cloudsplaining/command/scan_multi_account.py
cloudsplaining/command/scan_policy_file.py
cloudsplaining/output/__init__.py
cloudsplaining/output/policy_finding.py
cloudsplaining/output/report.py
cloudsplaining/output/template.html
cloudsplaining/output/dist/index.html
cloudsplaining/output/dist/js/chunk-vendors.js
cloudsplaining/output/dist/js/index.js
cloudsplaining/output/public/index.html
cloudsplaining/output/src/App.vue
cloudsplaining/output/src/main.js
cloudsplaining/output/src/sampleData.js
cloudsplaining/output/src/assets/1-overview.md
cloudsplaining/output/src/assets/2-triage-guidance.md
cloudsplaining/output/src/assets/3-remediation-guidance.md
cloudsplaining/output/src/assets/4-validation.md
cloudsplaining/output/src/assets/definition-assumable-by-compute-service.md
cloudsplaining/output/src/assets/definition-credentials-exposure.md
cloudsplaining/output/src/assets/definition-data-exfiltration.md
cloudsplaining/output/src/assets/definition-infrastructure-modification.md
cloudsplaining/output/src/assets/definition-privilege-escalation.md
cloudsplaining/output/src/assets/definition-resource-exposure.md
cloudsplaining/output/src/assets/definition-service-wildcard.md
cloudsplaining/output/src/assets/glossary.md
cloudsplaining/output/src/assets/how-do-i-validate-results.md
cloudsplaining/output/src/assets/identifying-false-positives.md
cloudsplaining/output/src/assets/logo.png
cloudsplaining/output/src/assets/summary.md
cloudsplaining/output/src/assets/what-should-i-do.md
cloudsplaining/output/src/components/Appendix.vue
cloudsplaining/output/src/components/Button.vue
cloudsplaining-0.8.2.dist-info/LICENSE
cloudsplaining-0.8.2.dist-info/METADATA
cloudsplaining-0.8.2.dist-info/WHEEL
cloudsplaining-0.8.2.dist-info/entry_points.txt
cloudsplaining-0.8.2.dist-info/top_level.txt
cloudsplaining-0.8.2.dist-info/zip-safe
cloudsplaining-0.8.2.dist-info/RECORD
