Metadata-Version: 2.1
Name: cloudsplaining
Version: 0.8.2
Summary: AWS IAM Security Assessment tool that identifies violations of least privilege and generates a risk-prioritized HTML report.
Home-page: https://github.com/salesforce/cloudsplaining
Author: Kinnaird McQuade
Author-email: kinnairdm@gmail.com
License: UNKNOWN
Project-URL: Documentation, https://policy-sentry.readthedocs.io/
Project-URL: Example Report, https://opensource.salesforce.com/cloudsplaining
Project-URL: Code, https://github.com/salesforce/cloudsplaining/
Project-URL: Twitter, https://twitter.com/kmcquade3
Project-URL: Red Team Report, https://opensource.salesforce.com/policy_sentry
Keywords: aws iam roles policy policies privileges security
Platform: UNKNOWN
Classifier: Programming Language :: Python :: 3 :: Only
Classifier: Programming Language :: Python :: 3.9
Classifier: Programming Language :: Python :: 3.10
Classifier: Programming Language :: Python :: 3.11
Classifier: Programming Language :: Python :: 3.12
Classifier: Programming Language :: Python :: 3.13
Classifier: Programming Language :: Python :: 3.14
Classifier: License :: OSI Approved :: MIT License
Classifier: Operating System :: OS Independent
Requires-Python: >=3.9
License-File: LICENSE
Requires-Dist: boto3
Requires-Dist: botocore
Requires-Dist: cached-property
Requires-Dist: click
Requires-Dist: click-option-group
Requires-Dist: jinja2
Requires-Dist: markdown
Requires-Dist: policy-sentry<0.15,>=0.14.0
Requires-Dist: pyyaml
Requires-Dist: schema
